{
  "recentFiles": [
    {
      "basename": "Thread",
      "path": "OS/Thread/canvas/Thread.canvas"
    },
    {
      "basename": "DeadLock",
      "path": "OS/Concurrency/canvas/DeadLock.canvas"
    },
    {
      "basename": "식사하는 철학자 문제",
      "path": "OS/Concurrency/canvas/식사하는 철학자 문제.md"
    },
    {
      "basename": "교착상태 발견 특징",
      "path": "OS/Concurrency/canvas/교착상태 발견 특징.md"
    },
    {
      "basename": "교착상태 회피 단점",
      "path": "OS/Concurrency/canvas/교착상태 회피 단점.md"
    },
    {
      "basename": "프로세스 시작 거부",
      "path": "OS/Concurrency/canvas/프로세스 시작 거부.md"
    },
    {
      "basename": "자원 할당 거부(은행원 알고리즘)",
      "path": "OS/Concurrency/canvas/자원 할당 거부(은행원 알고리즘).md"
    },
    {
      "basename": "교착상태 회복(recovery) 알고리즘",
      "path": "OS/Concurrency/canvas/교착상태 회복(recovery) 알고리즘.md"
    },
    {
      "basename": "교착상태 발견(deadlock detection)",
      "path": "OS/Concurrency/canvas/교착상태 발견(deadlock detection).md"
    },
    {
      "basename": "교착상태 회피 장점",
      "path": "OS/Concurrency/canvas/교착상태 회피 장점.md"
    },
    {
      "basename": "교착상태 회피(deadlock avoidance)",
      "path": "OS/Concurrency/canvas/교착상태 회피(deadlock avoidance).md"
    },
    {
      "basename": "교착상태 예방(deadlock prevention)",
      "path": "OS/Concurrency/canvas/교착상태 예방(deadlock prevention).md"
    },
    {
      "basename": "교착상태 발생 조건",
      "path": "OS/Concurrency/canvas/교착상태 발생 조건.md"
    },
    {
      "basename": "교착상태(DeadLock)",
      "path": "OS/Concurrency/canvas/교착상태(DeadLock).md"
    },
    {
      "basename": "프로세스에서의 자원 이용",
      "path": "OS/Concurrency/canvas/프로세스에서의 자원 이용.md"
    },
    {
      "basename": "Pasted image 20231217204644",
      "path": "Pasted image 20231217204644.png"
    },
    {
      "basename": "Semaphore",
      "path": "OS/Concurrency/canvas/Semaphore.canvas"
    },
    {
      "basename": "semWait(x) 연산 (P 연산)",
      "path": "OS/Concurrency/md/semWait(x) 연산 (P 연산).md"
    },
    {
      "basename": "이진 세마포어",
      "path": "OS/Concurrency/md/이진 세마포어.md"
    },
    {
      "basename": "쓰레드",
      "path": "OS/Thread/md/쓰레드.md"
    },
    {
      "basename": "커널 수준 쓰레드(KLT)",
      "path": "OS/Thread/md/커널 수준 쓰레드(KLT).md"
    },
    {
      "basename": "사용자 수준 쓰레드(ULT)",
      "path": "OS/Thread/md/사용자 수준 쓰레드(ULT).md"
    },
    {
      "basename": "Virtual Thread",
      "path": "Java/Virtual Thread/canvas/Virtual Thread.canvas"
    },
    {
      "basename": "Virtual Thread 비교",
      "path": "Java/Virtual Thread/resources/Virtual Thread 비교.png"
    },
    {
      "basename": "GSLB",
      "path": "Network/GSLB/canvas/GSLB.canvas"
    },
    {
      "basename": "URL",
      "path": "HTTP/URL/canvas/URL.canvas"
    },
    {
      "basename": "GSLB Policy",
      "path": "Network/GSLB/resources/GSLB Policy.png"
    },
    {
      "basename": "GSLB(Global Server Load Balancing)",
      "path": "Network/GSLB/md/GSLB(Global Server Load Balancing).md"
    },
    {
      "basename": "semaphore code",
      "path": "OS/Concurrency/resources/semaphore code.png"
    },
    {
      "basename": "Pasted image 20231212002734",
      "path": "Network/NAT/resources/Pasted image 20231212002734.png"
    },
    {
      "basename": "Pasted image 20231213173343",
      "path": "Network/GSLB/resources/Pasted image 20231213173343.png"
    },
    {
      "basename": "Pasted image 20231213173653",
      "path": "Network/GSLB/resources/Pasted image 20231213173653.png"
    },
    {
      "basename": "Pasted image 20231213173413",
      "path": "Network/GSLB/resources/Pasted image 20231213173413.png"
    },
    {
      "basename": "Pasted image 20231212003842",
      "path": "Network/NAT/resources/Pasted image 20231212003842.png"
    },
    {
      "basename": "Pasted image 20231212003703",
      "path": "Network/NAT/resources/Pasted image 20231212003703.png"
    },
    {
      "basename": "NAT",
      "path": "Network/NAT/canvas/NAT.canvas"
    },
    {
      "basename": "NAT(Network Address Translation)",
      "path": "Network/NAT/md/NAT(Network Address Translation).md"
    },
    {
      "basename": "SQL",
      "path": "DB/SQL/canvas/SQL.canvas"
    },
    {
      "basename": "인덱스를 사용하는 것이 좋은지 판단",
      "path": "DB/SQL/md/인덱스를 사용하는 것이 좋은지 판단.md"
    },
    {
      "basename": "인덱스를 사용할 수 없는 경우 대처",
      "path": "DB/SQL/md/인덱스를 사용할 수 없는 경우 대처.md"
    },
    {
      "basename": "인덱스를 사용할 수 없는 경우",
      "path": "DB/SQL/md/인덱스를 사용할 수 없는 경우.md"
    },
    {
      "basename": "정규화",
      "path": "DB/Normalization/canvas/정규화.canvas"
    },
    {
      "basename": "Hash 트레이드오프",
      "path": "DB/SQL/md/Hash 트레이드오프.md"
    },
    {
      "basename": "all-to-all session replication",
      "path": "Web/Session/resources/all-to-all session replication.png"
    },
    {
      "basename": "Integrated Session Storage",
      "path": "Web/Session/resources/Integrated Session Storage.png"
    },
    {
      "basename": "memcached",
      "path": "Web/Session/resources/memcached.png"
    },
    {
      "basename": "primary-secondary session replication",
      "path": "Web/Session/resources/primary-secondary session replication.png"
    },
    {
      "basename": "Session per WAS",
      "path": "Web/Session/resources/Session per WAS.png"
    },
    {
      "basename": "Cache 전략",
      "path": "DB/Cache/canvas/Cache 전략.canvas"
    },
    {
      "basename": "DB Replication",
      "path": "Web/Session/resources/DB Replication.png"
    }
  ],
  "omittedPaths": [],
  "maxLength": null,
  "openType": "tab"
}